setup.py
gdANN/__init__.py
gdANN/functions.py
gdANN.egg-info/PKG-INFO
gdANN.egg-info/SOURCES.txt
gdANN.egg-info/dependency_links.txt
gdANN.egg-info/top_level.txt