Metadata-Version: 2.1
Name: gdANN
Version: 4.1
Summary: contains neural network modules, activation functions and other useful stuff
Author: Gordon_Shi
Author-email: gordon2028261@concordiashanghai.org
Classifier: Programming Language :: Python :: 3
Classifier: Operating System :: OS Independent
